smtdata_lake_reports/__init__.py
smtdata_lake_reports/athena/__init__.py
smtdata_lake_reports/athena/execute.py
smtdata_lake_reports/athena/internal/AthenaClient.py
smtdata_lake_reports/athena/internal/AthenaUserspaceWriter.py
smtdata_lake_reports/athena/internal/__init__.py
smtdata_lake_reports/athena/internal/safe_sql.py
smtdata_lake_reports/inputs.py
smtdata_lake_reports/internal/InboxClient.py
smtdata_lake_reports/internal/InboxClientTypes.py
smtdata_lake_reports/internal/__init__.py
smtdata_lake_reports/logger.py
smtdata_lake_reports/runtime_context.py
smtdata_lake_reports/s3/S3Client.py
smtdata_lake_reports/s3/__init__.py
smtdata_lake_reports-1.6.1.dist-info/WHEEL
smtdata_lake_reports-1.6.1.dist-info/entry_points.txt
smtdata_lake_reports-1.6.1.dist-info/METADATA
smtdata_lake_reports-1.6.1.dist-info/RECORD
