Metadata-Version: 2.3
Name: smtdata-lake-reports
Version: 1.6.1
Summary: Python SDK for building Lake Reports in SMT Data ITBI Cloud
Requires-Dist: arrow>=1.3.0
Requires-Dist: boto3>=1.40.15,<1.42.1
Requires-Dist: fsspec>=2025.9.0
Requires-Dist: loguru>=0.7.3
Requires-Dist: pandas>=2.3.2
Requires-Dist: pyarrow>=21.0.0
Requires-Dist: pydantic>=2.11.7
Requires-Dist: pydantic-settings>=2.10.1
Requires-Dist: s3fs>=2025.9.0
Requires-Dist: sqlalchemy>=2.0.43
Requires-Dist: sqlalchemy-trino>=0.5.0
Requires-Dist: sqlglot>=27.12.0
Requires-Python: >=3.11
